[
{
"acceleration": -2.0000000000000004,
"curvature": -0.0,
"pose": {
"rotation": {
"radians": 3.141592653589793
},
"translation": {
"x": 1.95,
"y": 2.2
}
},
"time": 0.0,
"velocity": -0.0
},
{
"acceleration": -1.9999999999999998,
"curvature": -0.0,
"pose": {
"rotation": {
"radians": 3.141592653589793
},
"translation": {
"x": 2.0161046504974367,
"y": 2.2
}
},
"time": 0.25710824665388843,
"velocity": -0.514216493307777
},
{
"acceleration": -2.0,
"curvature": -0.0,
"pose": {
"rotation": {
"radians": 3.141592653589793
},
"translation": {
"x": 2.101084899902344,
"y": 2.2
}
},
"time": 0.3886964109717813,
"velocity": -0.7773928219435627
},
{
"acceleration": -2.0,
"curvature": -0.0,
"pose": {
"rotation": {
"radians": 3.141592653589793
},
"translation": {
"x": 2.2167496204376222,
"y": 2.2
}
},
"time": 0.5164780928922563,
"velocity": -1.0329561857845129
},
{
"acceleration": -2.0,
"curvature": -0.0,
"pose": {
"rotation": {
"radians": 3.141592653589793
},
"translation": {
"x": 2.2879178121685984,
"y": 2.2
}
},
"time": 0.5813069861687525,
"velocity": -1.1626139723375053
},
{
"acceleration": -2.0,
"curvature": -0.0,
"pose": {
"rotation": {
"radians": 3.141592653589793
},
"translation": {
"x": 2.368212890625,
"y": 2.2
}
},
"time": 0.646693815205465,
"velocity": -1.2933876304109302
},
{
"acceleration": -2.0,
"curvature": -0.0,
"pose": {
"rotation": {
"radians": 3.141592653589793
},
"translation": {
"x": 2.457411114871502,
"y": 2.2
}
},
"time": 0.7123279545767539,
"velocity": -1.424655909153508
},
{
"acceleration": -2.000000000000002,
"curvature": -0.0,
"pose": {
"rotation": {
"radians": 3.141592653589793
},
"translation": {
"x": 2.5550097942352297,
"y": 2.2
}
},
"time": 0.7778237552525826,
"velocity": -1.5556475105051655
},
{
"acceleration": -2.0,
"curvature": -0.0,
"pose": {
"rotation": {
"radians": 3.141592653589793
},
"translation": {
"x": 2.660262157022953,
"y": 2.2
}
},
"time": 0.8427705245337861,
"velocity": -1.6855410490675726
},
{
"acceleration": -2.0,
"curvature": -0.0,
"pose": {
"rotation": {
"radians": 3.141592653589793
},
"translation": {
"x": 2.7722122192382814,
"y": 2.2
}
},
"time": 0.9067591848105434,
"velocity": -1.8135183696210873
},
{
"acceleration": -0.9895389728994296,
"curvature": -0.0,
"pose": {
"rotation": {
"radians": 3.141592653589793
},
"translation": {
"x": 2.889729653298855,
"y": 2.2
}
},
"time": 0.9693965407916694,
"velocity": -1.9387930815833392
},
{
"acceleration": -0.0,
"curvature": -0.0,
"pose": {
"rotation": {
"radians": 3.141592653589793
},
"translation": {
"x": 3.01154465675354,
"y": 2.2
}
},
"time": 1.0312505153120661,
"velocity": -2.0
},
{
"acceleration": -0.0,
"curvature": -0.0,
"pose": {
"rotation": {
"radians": 3.141592653589793
},
"translation": {
"x": 3.1362828209996225,
"y": 2.2
}
},
"time": 1.0936195974351073,
"velocity": -2.0
},
{
"acceleration": -0.0,
"curvature": -0.0,
"pose": {
"rotation": {
"radians": 3.141592653589793
},
"translation": {
"x": 3.2625,
"y": 2.2
}
},
"time": 1.156728186935296,
"velocity": -2.0
},
{
"acceleration": -0.0,
"curvature": -0.0,
"pose": {
"rotation": {
"radians": 3.141592653589793
},
"translation": {
"x": 3.388717179000378,
"y": 2.2
}
},
"time": 1.219836776435485,
"velocity": -2.0
},
{
"acceleration": 0.9895389728993804,
"curvature": -0.0,
"pose": {
"rotation": {
"radians": 3.141592653589793
},
"translation": {
"x": 3.51345534324646,
"y": 2.2
}
},
"time": 1.282205858558526,
"velocity": -2.0
},
{
"acceleration": 2.0,
"curvature": -0.0,
"pose": {
"rotation": {
"radians": 3.141592653589793
},
"translation": {
"x": 3.6352703467011453,
"y": 2.2
}
},
"time": 1.3440598330789226,
"velocity": -1.9387930815833423
},
{
"acceleration": 2.0,
"curvature": -0.0,
"pose": {
"rotation": {
"radians": 3.141592653589793
},
"translation": {
"x": 3.752787780761719,
"y": 2.2
}
},
"time": 1.4066971890600484,
"velocity": -1.8135183696210906
},
{
"acceleration": 2.0,
"curvature": -0.0,
"pose": {
"rotation": {
"radians": 3.141592653589793
},
"translation": {
"x": 3.864737842977047,
"y": 2.2
}
},
"time": 1.4706858493368056,
"velocity": -1.6855410490675762
},
{
"acceleration": 2.000000000000002,
"curvature": -0.0,
"pose": {
"rotation": {
"radians": 3.141592653589793
},
"translation": {
"x": 3.9699902057647707,
"y": 2.2
}
},
"time": 1.535632618618009,
"velocity": -1.5556475105051697
},
{
"acceleration": 1.9999999999999976,
"curvature": -0.0,
"pose": {
"rotation": {
"radians": 3.141592653589793
},
"translation": {
"x": 4.067588885128499,
"y": 2.2
}
},
"time": 1.601128419293838,
"velocity": -1.4246559091535114
},
{
"acceleration": 2.0,
"curvature": -0.0,
"pose": {
"rotation": {
"radians": 3.141592653589793
},
"translation": {
"x": 4.156787109375001,
"y": 2.2
}
},
"time": 1.6667625586651267,
"velocity": -1.293387630410934
},
{
"acceleration": 2.0,
"curvature": -0.0,
"pose": {
"rotation": {
"radians": 3.141592653589793
},
"translation": {
"x": 4.237082187831403,
"y": 2.2
}
},
"time": 1.7321493877018388,
"velocity": -1.1626139723375095
},
{
"acceleration": 2.0,
"curvature": -0.0,
"pose": {
"rotation": {
"radians": 3.141592653589793
},
"translation": {
"x": 4.30825037956238,
"y": 2.2
}
},
"time": 1.7969782809783355,
"velocity": -1.032956185784516
},
{
"acceleration": 2.0,
"curvature": -0.0,
"pose": {
"rotation": {
"radians": 3.141592653589793
},
"translation": {
"x": 4.423915100097658,
"y": 2.2
}
},
"time": 1.9247599628988101,
"velocity": -0.7773928219435667
},
{
"acceleration": 2.0,
"curvature": -0.0,
"pose": {
"rotation": {
"radians": 3.141592653589793
},
"translation": {
"x": 4.508895349502567,
"y": 2.2
}
},
"time": 2.0563481272167055,
"velocity": -0.5142164933077761
},
{
"acceleration": 2.0,
"curvature": -0.0,
"pose": {
"rotation": {
"radians": 3.141592653589793
},
"translation": {
"x": 4.575000000000004,
"y": 2.2
}
},
"time": 2.3134563738705936,
"velocity": -0.0
}
]